{
  "id": "es6",
  "source": "caniuse",
  "name": "ECMAScript 2015 (ES6)",
  "description": "Support for the ECMAScript 2015 specification. Features include Promises, Modules, Classes, Template Literals, Arrow Functions, Let and Const, Default Parameters, Generators, Destructuring Assignment, Rest & Spread, Map/Set & WeakMap/WeakSet and many more.",
  "category": "JS API",
  "links": [
    {
      "url": "http://es6-features.org",
      "title": "ES6 New features: overview and comparisons"
    },
    {
      "url": "https://exploringjs.com/es6/",
      "title": "Exploring ES6 (book)"
    },
    {
      "url": "https://github.com/zloirock/core-js#ecmascript",
      "title": "Polyfill for all possible ES2015 features is available in the core-js library"
    }
  ],
  "support": {
    "chrome": {
      "current": "u",
      "firstPartial": "21"
    },
    "firefox": {
      "current": "u",
      "firstPartial": "6"
    },
    "safari": {
      "current": "y",
      "firstFull": "10",
      "firstPartial": "7.1"
    },
    "edge": {
      "current": "u"
    },
    "opera": {
      "current": "u",
      "firstPartial": "15"
    },
    "ie": {
      "current": "u"
    },
    "ios_saf": {
      "current": "y",
      "firstFull": "10.0-10.2",
      "firstPartial": "7.0-7.1"
    },
    "and_chr": {
      "current": "u"
    },
    "samsung": {
      "current": "u",
      "firstPartial": "4"
    },
    "and_ff": {
      "current": "u"
    }
  },
  "usage": {
    "global": {
      "full": 96.23,
      "partial": 0.58,
      "total": 96.81
    },
    "byBrowser": {
      "desktop": {
        "chrome": 27.41,
        "firefox": 1.82,
        "safari": 1.42,
        "opera": 0.91
      },
      "mobile": {
        "ios_saf": 12.22,
        "samsung": 1.93
      }
    },
    "type": "actual"
  },
  "notes": {
    "general": "As ES6 refers to a huge specification and browsers have various levels of support, \"Supported\" means at least 95% of the spec is supported. \"Partial support\" refers to at least 10% of the spec being supported. For full details see the [Kangax ES6 support table](https://compat-table.github.io/compat-table/es6/).",
    "byNum": {
      "1": "Notable partial support in IE11 includes (at least some) support for `const`, `let`, block-level function declaration, typed arrays, `Map`, `Set` and `WeakMap`.",
      "2": "Does not support [tail call optimization](https://compat-table.github.io/compat-table/es6/#test-proper_tail_calls_%28tail_call_optimisation%29)",
      "3": "Only has partial Symbol support and partial support for `RegExp.prototype` properties"
    }
  },
  "baseline": false,
  "sourceData": {
    "primary": {
      "source": "caniuse",
      "id": "es6"
    },
    "supplementary": []
  },
  "caniuseUrl": "https://caniuse.com/?search=es6"
}