{
  "id": "input-search",
  "source": "caniuse",
  "name": "Search input type",
  "description": "Search field form input type. Intended to look like the underlying platform's native search field widget (if there is one). Other than its appearance, it's the same as an `<input type=\"text\">`.",
  "category": "HTML5",
  "mdn": "https://developer.mozilla.org/docs/Web/HTML/Reference/Elements/input/search",
  "links": [
    {
      "url": "https://css-tricks.com/webkit-html5-search-inputs/",
      "title": "CSS-Tricks article"
    },
    {
      "url": "https://www.wufoo.com/html5/types/5-search.html",
      "title": "Wufoo's The Current State of HTML5 Forms: The search Type"
    }
  ],
  "support": {
    "chrome": {
      "current": "y",
      "firstFull": "26"
    },
    "firefox": {
      "current": "u"
    },
    "safari": {
      "current": "y",
      "firstFull": "5.1"
    },
    "edge": {
      "current": "y",
      "firstFull": "79"
    },
    "opera": {
      "current": "y",
      "firstFull": "11.6"
    },
    "ie": {
      "current": "u"
    },
    "ios_saf": {
      "current": "y",
      "firstFull": "5.0-5.1"
    },
    "and_chr": {
      "current": "y",
      "firstFull": "143"
    },
    "samsung": {
      "current": "y",
      "firstFull": "4"
    },
    "and_ff": {
      "current": "u"
    }
  },
  "usage": {
    "global": {
      "full": 96.88,
      "partial": 0,
      "total": 96.88
    },
    "byBrowser": {
      "desktop": {
        "chrome": 27.41,
        "safari": 1.42,
        "edge": 4.26,
        "opera": 0.91
      },
      "mobile": {
        "ios_saf": 12.23,
        "and_chr": 44.12,
        "samsung": 1.93
      }
    },
    "type": "actual"
  },
  "notes": {
    "general": "",
    "byNum": {
      "1": "Does not use a special search-specific UI for the field, just the same UI as a regular `<input type=\"text\">`."
    }
  },
  "baseline": "high",
  "sourceData": {
    "primary": {
      "source": "caniuse",
      "id": "input-search"
    },
    "supplementary": [
      {
        "source": "webfeatures",
        "id": "search-input-type",
        "matched": "exact"
      },
      {
        "source": "mdnbcd",
        "id": "html.elements.input.type_search",
        "matched": "via-webfeatures"
      }
    ]
  },
  "caniuseUrl": "https://caniuse.com/?search=input-search"
}