{
  "id": "link-icon-png",
  "source": "caniuse",
  "name": "PNG favicons",
  "description": "Icon used by browsers to identify a webpage or site. While all browsers support the `.ico` format, the PNG format can be preferable.",
  "category": "HTML5",
  "links": [
    {
      "url": "https://dev.to/masakudamatsu/favicon-nightmare-how-to-maintain-sanity-3al7",
      "title": "How to favicon in 2021"
    }
  ],
  "support": {
    "chrome": {
      "current": "y",
      "firstFull": "4"
    },
    "firefox": {
      "current": "y",
      "firstFull": "2"
    },
    "safari": {
      "current": "y",
      "firstFull": "3.1"
    },
    "edge": {
      "current": "y",
      "firstFull": "12"
    },
    "opera": {
      "current": "y",
      "firstFull": "9"
    },
    "ie": {
      "current": "y",
      "firstFull": "11"
    },
    "ios_saf": {
      "current": "y",
      "firstFull": "12.0-12.1"
    },
    "and_chr": {
      "current": "y",
      "firstFull": "143"
    },
    "samsung": {
      "current": "y",
      "firstFull": "4"
    },
    "and_ff": {
      "current": "y",
      "firstFull": "146"
    }
  },
  "usage": {
    "global": {
      "full": 96.59,
      "partial": 0,
      "total": 96.59
    },
    "byBrowser": {
      "desktop": {
        "chrome": 27.41,
        "firefox": 1.85,
        "safari": 1.42,
        "edge": 4.26,
        "opera": 0.91,
        "ie": 0.36
      },
      "mobile": {
        "ios_saf": 11.97,
        "and_chr": 44.12,
        "samsung": 1.93,
        "and_ff": 0.31
      }
    },
    "type": "actual"
  },
  "notes": {
    "general": "Favicon support is a complicated topic. See [this guide](https://dev.to/masakudamatsu/favicon-nightmare-how-to-maintain-sanity-3al7) for more information.\r\n\r\nSee also [SVG favicons](/link-icon-svg).",
    "byNum": {
      "1": "Does not use favicons at all (but may have alternative for bookmarks, etc.)."
    }
  },
  "baseline": false,
  "sourceData": {
    "primary": {
      "source": "caniuse",
      "id": "link-icon-png"
    },
    "supplementary": []
  }
}