{
  "id": "mdn-api.ReadableStream.from_static",
  "source": "mdnbcd",
  "name": "`from()` static method",
  "description": "`from()` static method",
  "category": "JS API",
  "mdn": "https://developer.mozilla.org/docs/Web/API/ReadableStream/from_static",
  "links": [],
  "support": {
    "ffx": {
      "current": "y",
      "firstFull": "117"
    },
    "chr": {
      "current": "n"
    },
    "saf": {
      "current": "n"
    },
    "edg": {
      "current": "n"
    },
    "opr": {
      "current": "n"
    },
    "ie": {
      "current": "n"
    },
    "ios_saf": {
      "current": "n"
    },
    "an_chr": {
      "current": "n"
    },
    "smsg": {
      "current": "n"
    },
    "an_ff": {
      "current": "y",
      "firstFull": "117"
    }
  },
  "usage": {
    "global": {
      "full": 1.91,
      "partial": 0,
      "total": 1.91
    },
    "byBrowser": {
      "desktop": {
        "ffx": 1.6
      },
      "mobile": {
        "an_ff": 0.31
      }
    },
    "type": "estimated"
  },
  "baseline": false,
  "sourceData": {
    "primary": {
      "source": "mdnbcd",
      "id": "api.ReadableStream.from_static"
    },
    "supplementary": [
      {
        "source": "webfeatures",
        "id": "readablestream-from",
        "matched": "exact"
      }
    ]
  },
  "caniuseUrl": "https://caniuse.com/?search=%60from()%60%20static%20method"
}