{
  "id": "mdn-css.properties.text-indent.hanging",
  "source": "mdnbcd",
  "name": "text-indent: Hanging",
  "description": "",
  "category": "CSS",
  "links": [],
  "support": {
    "chr": {
      "current": "y",
      "firstFull": "146"
    },
    "ffx": {
      "current": "y",
      "firstFull": "121"
    },
    "saf": {
      "current": "y",
      "firstFull": "15"
    },
    "edg": {
      "current": "y",
      "firstFull": "146"
    },
    "opr": {
      "current": "y",
      "firstFull": "146"
    },
    "ie": {
      "current": "y",
      "firstFull": "146"
    },
    "ios_saf": {
      "current": "y",
      "firstFull": "15"
    },
    "an_chr": {
      "current": "y",
      "firstFull": "146"
    },
    "smsg": {
      "current": "y",
      "firstFull": "146"
    },
    "an_ff": {
      "current": "y",
      "firstFull": "121"
    }
  },
  "usage": {
    "global": {
      "full": 59.14,
      "partial": 0,
      "total": 59.14
    },
    "byBrowser": {
      "desktop": {
        "ffx": 1.48,
        "saf": 1.37
      },
      "mobile": {
        "ios_saf": 11.86,
        "an_chr": 44.12,
        "an_ff": 0.31
      }
    },
    "type": "estimated"
  },
  "baseline": false,
  "sourceData": {
    "primary": {
      "source": "mdnbcd",
      "id": "css.properties.text-indent.hanging"
    },
    "supplementary": [
      {
        "source": "webfeatures",
        "id": "text-indent-hanging",
        "matched": "exact"
      }
    ]
  },
  "caniuseUrl": "https://caniuse.com/?search=text-indent%3A%20Hanging"
}