{
  "id": "mdn-api.MediaDevices.getSupportedConstraints.return_object_property_latency",
  "source": "mdnbcd",
  "name": "<code>latency</code> property in returned object",
  "description": "<code>latency</code> property in returned object",
  "category": "JS API",
  "mdn": "https://developer.mozilla.org/docs/Web/API/MediaTrackConstraints/latency",
  "links": [],
  "support": {
    "chrome": {
      "current": "y",
      "firstFull": "53"
    },
    "edge": {
      "current": "y",
      "firstFull": "79"
    },
    "opera": {
      "current": "y",
      "firstFull": "40"
    },
    "firefox": {
      "current": "n"
    },
    "safari": {
      "current": "n"
    },
    "ie": {
      "current": "y",
      "firstFull": "79"
    },
    "ios_saf": {
      "current": "n"
    },
    "and_chr": {
      "current": "y",
      "firstFull": "53"
    },
    "samsung": {
      "current": "y",
      "firstFull": "53"
    },
    "and_ff": {
      "current": "n"
    }
  },
  "usage": {
    "global": {
      "full": 76.56,
      "partial": 0,
      "total": 76.56
    },
    "byBrowser": {
      "desktop": {
        "chrome": 27.27,
        "edge": 4.26,
        "opera": 0.91
      },
      "mobile": {
        "and_chr": 44.12
      }
    },
    "type": "estimated"
  },
  "baseline": false,
  "sourceData": {
    "primary": {
      "source": "mdnbcd",
      "id": "api.MediaDevices.getSupportedConstraints.return_object_property_latency"
    },
    "supplementary": []
  },
  "caniuseUrl": "https://caniuse.com/?search=mdn-api.MediaDevices.getSupportedConstraints.return_object_property_latency"
}