{
  "id": "mdn-api.GPUAdapter.requestAdapterInfo",
  "source": "mdnbcd",
  "name": "GPUAdapter.requestAdapterInfo",
  "description": "",
  "category": "JS API",
  "mdn": "https://developer.mozilla.org/docs/Web/API/GPUAdapter/requestAdapterInfo",
  "links": [],
  "support": {
    "chr": {
      "current": "y",
      "firstFull": "113"
    },
    "ffx": {
      "current": "a",
      "firstPartial": "141"
    },
    "edg": {
      "current": "y",
      "firstFull": "113"
    },
    "opr": {
      "current": "y",
      "firstFull": "99"
    },
    "saf": {
      "current": "n"
    },
    "ie": {
      "current": "y",
      "firstFull": "113"
    },
    "ios_saf": {
      "current": "n"
    },
    "an_chr": {
      "current": "y",
      "firstFull": "113"
    },
    "smsg": {
      "current": "y",
      "firstFull": "113"
    },
    "an_ff": {
      "current": "a",
      "firstPartial": "141"
    }
  },
  "usage": {
    "global": {
      "full": 72.55,
      "partial": 1.66,
      "total": 74.21
    },
    "byBrowser": {
      "desktop": {
        "chr": 23.42,
        "ffx": 1.35,
        "edg": 4.21,
        "opr": 0.79
      },
      "mobile": {
        "an_chr": 44.12,
        "an_ff": 0.31
      }
    },
    "type": "estimated"
  },
  "baseline": false,
  "sourceData": {
    "primary": {
      "source": "mdnbcd",
      "id": "api.GPUAdapter.requestAdapterInfo"
    },
    "supplementary": []
  },
  "caniuseUrl": "https://caniuse.com/?search=GPUAdapter.requestAdapterInfo"
}