{
  "id": "mdn-http.headers.Sec-CH-DPR",
  "source": "mdnbcd",
  "name": "`Sec-CH-DPR` request header",
  "description": "`Sec-CH-DPR` request header",
  "category": "Other",
  "mdn": "https://developer.mozilla.org/docs/Web/HTTP/Reference/Headers/Sec-CH-DPR",
  "links": [],
  "support": {
    "chr": {
      "current": "y",
      "firstFull": "97"
    },
    "edg": {
      "current": "y",
      "firstFull": "97"
    },
    "opr": {
      "current": "y",
      "firstFull": "83"
    },
    "ffx": {
      "current": "n"
    },
    "saf": {
      "current": "n"
    },
    "ie": {
      "current": "y",
      "firstFull": "97"
    },
    "ios_saf": {
      "current": "n"
    },
    "an_chr": {
      "current": "y",
      "firstFull": "97"
    },
    "smsg": {
      "current": "y",
      "firstFull": "97"
    },
    "an_ff": {
      "current": "n"
    }
  },
  "usage": {
    "global": {
      "full": 76.21,
      "partial": 0,
      "total": 76.21
    },
    "byBrowser": {
      "desktop": {
        "chr": 26.93,
        "edg": 4.25,
        "opr": 0.91
      },
      "mobile": {
        "an_chr": 44.12
      }
    },
    "type": "estimated"
  },
  "baseline": false,
  "sourceData": {
    "primary": {
      "source": "mdnbcd",
      "id": "http.headers.Sec-CH-DPR"
    },
    "supplementary": []
  },
  "caniuseUrl": "https://caniuse.com/?search=%60Sec-CH-DPR%60%20request%20header"
}