{
  "id": "webgl",
  "source": "caniuse",
  "name": "WebGL - 3D Canvas graphics",
  "description": "Method of generating dynamic 3D graphics using JavaScript, accelerated through hardware",
  "category": "Other",
  "mdn": "https://developer.mozilla.org/docs/Web/API/WebGLUniformLocation",
  "links": [
    {
      "url": "https://get.webgl.org/get-a-webgl-implementation/",
      "title": "Instructions on enabling WebGL"
    },
    {
      "url": "https://www.khronos.org/webgl/wiki/Tutorial",
      "title": "Tutorial"
    },
    {
      "url": "https://hacks.mozilla.org/2009/12/webgl-draft-released-today/",
      "title": "Firefox blog post"
    },
    {
      "url": "https://github.com/iewebgl/iewebgl",
      "title": "Polyfill for IE"
    }
  ],
  "support": {
    "chrome": {
      "current": "y",
      "firstFull": "33"
    },
    "firefox": {
      "current": "y",
      "firstFull": "24"
    },
    "safari": {
      "current": "y",
      "firstFull": "8"
    },
    "edge": {
      "current": "y",
      "firstFull": "79"
    },
    "opera": {
      "current": "y",
      "firstFull": "19"
    },
    "ie": {
      "current": "u"
    },
    "ios_saf": {
      "current": "y",
      "firstFull": "8"
    },
    "and_chr": {
      "current": "y",
      "firstFull": "143"
    },
    "samsung": {
      "current": "y",
      "firstFull": "4"
    },
    "and_ff": {
      "current": "y",
      "firstFull": "146"
    }
  },
  "usage": {
    "global": {
      "full": 96.83,
      "partial": 0,
      "total": 96.83
    },
    "byBrowser": {
      "desktop": {
        "chrome": 27.41,
        "firefox": 1.77,
        "safari": 1.42,
        "edge": 4.26,
        "opera": 0.91
      },
      "mobile": {
        "ios_saf": 12.22,
        "and_chr": 44.12,
        "samsung": 1.93,
        "and_ff": 0.31
      }
    },
    "type": "actual"
  },
  "notes": {
    "general": "WebGL support is dependent on GPU support and may not be available on older devices. This is due to the additional requirement for users to have [up to date video drivers](http://www.khronos.org/webgl/wiki/BlacklistsAndWhitelists).\r\n\r\nNote that WebGL is part of the [Khronos Group](http://www.khronos.org/webgl/), not the W3C.",
    "byNum": {
      "1": "WebGL context is accessed from \"experimental-webgl\" rather than \"webgl\""
    }
  },
  "baseline": "high",
  "sourceData": {
    "primary": {
      "source": "caniuse",
      "id": "webgl"
    },
    "supplementary": [
      {
        "source": "webfeatures",
        "id": "webgl",
        "matched": "exact"
      },
      {
        "source": "mdnbcd",
        "id": "api.HTMLCanvasElement.getContext.webgl_context",
        "matched": "via-webfeatures"
      },
      {
        "source": "mdnbcd",
        "id": "api.HTMLCanvasElement.getContext.webgl_context.options_alpha_parameter",
        "matched": "via-webfeatures"
      },
      {
        "source": "mdnbcd",
        "id": "api.HTMLCanvasElement.getContext.webgl_context.options_failIfMajorPerformanceCaveat_parameter",
        "matched": "via-webfeatures"
      },
      {
        "source": "mdnbcd",
        "id": "api.HTMLCanvasElement.getContext.webgl_context.options_powerPreference_parameter",
        "matched": "via-webfeatures"
      },
      {
        "source": "mdnbcd",
        "id": "api.HTMLCanvasElement.webglcontextcreationerror_event",
        "matched": "via-webfeatures"
      },
      {
        "source": "mdnbcd",
        "id": "api.HTMLCanvasElement.webglcontextlost_event",
        "matched": "via-webfeatures"
      },
      {
        "source": "mdnbcd",
        "id": "api.HTMLCanvasElement.webglcontextrestored_event",
        "matched": "via-webfeatures"
      },
      {
        "source": "mdnbcd",
        "id": "api.WebGLActiveInfo",
        "matched": "via-webfeatures"
      },
      {
        "source": "mdnbcd",
        "id": "api.WebGLActiveInfo.name",
        "matched": "via-webfeatures"
      },
      {
        "source": "mdnbcd",
        "id": "api.WebGLActiveInfo.size",
        "matched": "via-webfeatures"
      },
      {
        "source": "mdnbcd",
        "id": "api.WebGLActiveInfo.type",
        "matched": "via-webfeatures"
      },
      {
        "source": "mdnbcd",
        "id": "api.WebGLActiveInfo.worker_support",
        "matched": "via-webfeatures"
      },
      {
        "source": "mdnbcd",
        "id": "api.WebGLBuffer",
        "matched": "via-webfeatures"
      },
      {
        "source": "mdnbcd",
        "id": "api.WebGLBuffer.worker_support",
        "matched": "via-webfeatures"
      },
      {
        "source": "mdnbcd",
        "id": "api.WebGLContextEvent",
        "matched": "via-webfeatures"
      },
      {
        "source": "mdnbcd",
        "id": "api.WebGLContextEvent.WebGLContextEvent",
        "matched": "via-webfeatures"
      },
      {
        "source": "mdnbcd",
        "id": "api.WebGLContextEvent.statusMessage",
        "matched": "via-webfeatures"
      },
      {
        "source": "mdnbcd",
        "id": "api.WebGLContextEvent.worker_support",
        "matched": "via-webfeatures"
      },
      {
        "source": "mdnbcd",
        "id": "api.WebGLFramebuffer",
        "matched": "via-webfeatures"
      },
      {
        "source": "mdnbcd",
        "id": "api.WebGLFramebuffer.worker_support",
        "matched": "via-webfeatures"
      },
      {
        "source": "mdnbcd",
        "id": "api.WebGLObject",
        "matched": "via-webfeatures"
      },
      {
        "source": "mdnbcd",
        "id": "api.WebGLProgram",
        "matched": "via-webfeatures"
      },
      {
        "source": "mdnbcd",
        "id": "api.WebGLProgram.worker_support",
        "matched": "via-webfeatures"
      },
      {
        "source": "mdnbcd",
        "id": "api.WebGLRenderbuffer",
        "matched": "via-webfeatures"
      },
      {
        "source": "mdnbcd",
        "id": "api.WebGLRenderbuffer.worker_support",
        "matched": "via-webfeatures"
      },
      {
        "source": "mdnbcd",
        "id": "api.WebGLRenderingContext",
        "matched": "via-webfeatures"
      },
      {
        "source": "mdnbcd",
        "id": "api.WebGLRenderingContext.activeTexture",
        "matched": "via-webfeatures"
      },
      {
        "source": "mdnbcd",
        "id": "api.WebGLRenderingContext.attachShader",
        "matched": "via-webfeatures"
      },
      {
        "source": "mdnbcd",
        "id": "api.WebGLRenderingContext.bindAttribLocation",
        "matched": "via-webfeatures"
      },
      {
        "source": "mdnbcd",
        "id": "api.WebGLRenderingContext.bindBuffer",
        "matched": "via-webfeatures"
      },
      {
        "source": "mdnbcd",
        "id": "api.WebGLRenderingContext.bindFramebuffer",
        "matched": "via-webfeatures"
      },
      {
        "source": "mdnbcd",
        "id": "api.WebGLRenderingContext.bindRenderbuffer",
        "matched": "via-webfeatures"
      },
      {
        "source": "mdnbcd",
        "id": "api.WebGLRenderingContext.bindTexture",
        "matched": "via-webfeatures"
      },
      {
        "source": "mdnbcd",
        "id": "api.WebGLRenderingContext.blendColor",
        "matched": "via-webfeatures"
      },
      {
        "source": "mdnbcd",
        "id": "api.WebGLRenderingContext.blendEquation",
        "matched": "via-webfeatures"
      },
      {
        "source": "mdnbcd",
        "id": "api.WebGLRenderingContext.blendEquationSeparate",
        "matched": "via-webfeatures"
      },
      {
        "source": "mdnbcd",
        "id": "api.WebGLRenderingContext.blendFunc",
        "matched": "via-webfeatures"
      },
      {
        "source": "mdnbcd",
        "id": "api.WebGLRenderingContext.blendFuncSeparate",
        "matched": "via-webfeatures"
      },
      {
        "source": "mdnbcd",
        "id": "api.WebGLRenderingContext.bufferData",
        "matched": "via-webfeatures"
      },
      {
        "source": "mdnbcd",
        "id": "api.WebGLRenderingContext.bufferSubData",
        "matched": "via-webfeatures"
      },
      {
        "source": "mdnbcd",
        "id": "api.WebGLRenderingContext.canvas",
        "matched": "via-webfeatures"
      },
      {
        "source": "mdnbcd",
        "id": "api.WebGLRenderingContext.checkFramebufferStatus",
        "matched": "via-webfeatures"
      },
      {
        "source": "mdnbcd",
        "id": "api.WebGLRenderingContext.clear",
        "matched": "via-webfeatures"
      },
      {
        "source": "mdnbcd",
        "id": "api.WebGLRenderingContext.clearColor",
        "matched": "via-webfeatures"
      },
      {
        "source": "mdnbcd",
        "id": "api.WebGLRenderingContext.clearDepth",
        "matched": "via-webfeatures"
      },
      {
        "source": "mdnbcd",
        "id": "api.WebGLRenderingContext.clearStencil",
        "matched": "via-webfeatures"
      },
      {
        "source": "mdnbcd",
        "id": "api.WebGLRenderingContext.colorMask",
        "matched": "via-webfeatures"
      },
      {
        "source": "mdnbcd",
        "id": "api.WebGLRenderingContext.compileShader",
        "matched": "via-webfeatures"
      },
      {
        "source": "mdnbcd",
        "id": "api.WebGLRenderingContext.compressedTexImage2D",
        "matched": "via-webfeatures"
      },
      {
        "source": "mdnbcd",
        "id": "api.WebGLRenderingContext.compressedTexSubImage2D",
        "matched": "via-webfeatures"
      },
      {
        "source": "mdnbcd",
        "id": "api.WebGLRenderingContext.copyTexImage2D",
        "matched": "via-webfeatures"
      },
      {
        "source": "mdnbcd",
        "id": "api.WebGLRenderingContext.copyTexSubImage2D",
        "matched": "via-webfeatures"
      },
      {
        "source": "mdnbcd",
        "id": "api.WebGLRenderingContext.createBuffer",
        "matched": "via-webfeatures"
      },
      {
        "source": "mdnbcd",
        "id": "api.WebGLRenderingContext.createFramebuffer",
        "matched": "via-webfeatures"
      },
      {
        "source": "mdnbcd",
        "id": "api.WebGLRenderingContext.createProgram",
        "matched": "via-webfeatures"
      },
      {
        "source": "mdnbcd",
        "id": "api.WebGLRenderingContext.createRenderbuffer",
        "matched": "via-webfeatures"
      },
      {
        "source": "mdnbcd",
        "id": "api.WebGLRenderingContext.createShader",
        "matched": "via-webfeatures"
      },
      {
        "source": "mdnbcd",
        "id": "api.WebGLRenderingContext.createTexture",
        "matched": "via-webfeatures"
      },
      {
        "source": "mdnbcd",
        "id": "api.WebGLRenderingContext.cullFace",
        "matched": "via-webfeatures"
      },
      {
        "source": "mdnbcd",
        "id": "api.WebGLRenderingContext.deleteBuffer",
        "matched": "via-webfeatures"
      },
      {
        "source": "mdnbcd",
        "id": "api.WebGLRenderingContext.deleteFramebuffer",
        "matched": "via-webfeatures"
      },
      {
        "source": "mdnbcd",
        "id": "api.WebGLRenderingContext.deleteProgram",
        "matched": "via-webfeatures"
      },
      {
        "source": "mdnbcd",
        "id": "api.WebGLRenderingContext.deleteRenderbuffer",
        "matched": "via-webfeatures"
      },
      {
        "source": "mdnbcd",
        "id": "api.WebGLRenderingContext.deleteShader",
        "matched": "via-webfeatures"
      },
      {
        "source": "mdnbcd",
        "id": "api.WebGLRenderingContext.deleteTexture",
        "matched": "via-webfeatures"
      },
      {
        "source": "mdnbcd",
        "id": "api.WebGLRenderingContext.depthFunc",
        "matched": "via-webfeatures"
      },
      {
        "source": "mdnbcd",
        "id": "api.WebGLRenderingContext.depthMask",
        "matched": "via-webfeatures"
      },
      {
        "source": "mdnbcd",
        "id": "api.WebGLRenderingContext.depthRange",
        "matched": "via-webfeatures"
      },
      {
        "source": "mdnbcd",
        "id": "api.WebGLRenderingContext.detachShader",
        "matched": "via-webfeatures"
      },
      {
        "source": "mdnbcd",
        "id": "api.WebGLRenderingContext.disable",
        "matched": "via-webfeatures"
      },
      {
        "source": "mdnbcd",
        "id": "api.WebGLRenderingContext.disableVertexAttribArray",
        "matched": "via-webfeatures"
      },
      {
        "source": "mdnbcd",
        "id": "api.WebGLRenderingContext.drawArrays",
        "matched": "via-webfeatures"
      },
      {
        "source": "mdnbcd",
        "id": "api.WebGLRenderingContext.drawElements",
        "matched": "via-webfeatures"
      },
      {
        "source": "mdnbcd",
        "id": "api.WebGLRenderingContext.drawingBufferFormat",
        "matched": "via-webfeatures"
      },
      {
        "source": "mdnbcd",
        "id": "api.WebGLRenderingContext.drawingBufferHeight",
        "matched": "via-webfeatures"
      },
      {
        "source": "mdnbcd",
        "id": "api.WebGLRenderingContext.drawingBufferStorage",
        "matched": "via-webfeatures"
      },
      {
        "source": "mdnbcd",
        "id": "api.WebGLRenderingContext.drawingBufferWidth",
        "matched": "via-webfeatures"
      },
      {
        "source": "mdnbcd",
        "id": "api.WebGLRenderingContext.enable",
        "matched": "via-webfeatures"
      },
      {
        "source": "mdnbcd",
        "id": "api.WebGLRenderingContext.enableVertexAttribArray",
        "matched": "via-webfeatures"
      },
      {
        "source": "mdnbcd",
        "id": "api.WebGLRenderingContext.finish",
        "matched": "via-webfeatures"
      },
      {
        "source": "mdnbcd",
        "id": "api.WebGLRenderingContext.flush",
        "matched": "via-webfeatures"
      },
      {
        "source": "mdnbcd",
        "id": "api.WebGLRenderingContext.framebufferRenderbuffer",
        "matched": "via-webfeatures"
      },
      {
        "source": "mdnbcd",
        "id": "api.WebGLRenderingContext.framebufferTexture2D",
        "matched": "via-webfeatures"
      },
      {
        "source": "mdnbcd",
        "id": "api.WebGLRenderingContext.frontFace",
        "matched": "via-webfeatures"
      },
      {
        "source": "mdnbcd",
        "id": "api.WebGLRenderingContext.generateMipmap",
        "matched": "via-webfeatures"
      },
      {
        "source": "mdnbcd",
        "id": "api.WebGLRenderingContext.getActiveAttrib",
        "matched": "via-webfeatures"
      },
      {
        "source": "mdnbcd",
        "id": "api.WebGLRenderingContext.getActiveUniform",
        "matched": "via-webfeatures"
      },
      {
        "source": "mdnbcd",
        "id": "api.WebGLRenderingContext.getAttachedShaders",
        "matched": "via-webfeatures"
      },
      {
        "source": "mdnbcd",
        "id": "api.WebGLRenderingContext.getAttribLocation",
        "matched": "via-webfeatures"
      },
      {
        "source": "mdnbcd",
        "id": "api.WebGLRenderingContext.getBufferParameter",
        "matched": "via-webfeatures"
      },
      {
        "source": "mdnbcd",
        "id": "api.WebGLRenderingContext.getContextAttributes",
        "matched": "via-webfeatures"
      },
      {
        "source": "mdnbcd",
        "id": "api.WebGLRenderingContext.getError",
        "matched": "via-webfeatures"
      },
      {
        "source": "mdnbcd",
        "id": "api.WebGLRenderingContext.getExtension",
        "matched": "via-webfeatures"
      },
      {
        "source": "mdnbcd",
        "id": "api.WebGLRenderingContext.getFramebufferAttachmentParameter",
        "matched": "via-webfeatures"
      },
      {
        "source": "mdnbcd",
        "id": "api.WebGLRenderingContext.getParameter",
        "matched": "via-webfeatures"
      },
      {
        "source": "mdnbcd",
        "id": "api.WebGLRenderingContext.getProgramInfoLog",
        "matched": "via-webfeatures"
      },
      {
        "source": "mdnbcd",
        "id": "api.WebGLRenderingContext.getProgramParameter",
        "matched": "via-webfeatures"
      },
      {
        "source": "mdnbcd",
        "id": "api.WebGLRenderingContext.getRenderbufferParameter",
        "matched": "via-webfeatures"
      },
      {
        "source": "mdnbcd",
        "id": "api.WebGLRenderingContext.getShaderInfoLog",
        "matched": "via-webfeatures"
      },
      {
        "source": "mdnbcd",
        "id": "api.WebGLRenderingContext.getShaderParameter",
        "matched": "via-webfeatures"
      },
      {
        "source": "mdnbcd",
        "id": "api.WebGLRenderingContext.getShaderPrecisionFormat",
        "matched": "via-webfeatures"
      },
      {
        "source": "mdnbcd",
        "id": "api.WebGLRenderingContext.getShaderSource",
        "matched": "via-webfeatures"
      },
      {
        "source": "mdnbcd",
        "id": "api.WebGLRenderingContext.getSupportedExtensions",
        "matched": "via-webfeatures"
      },
      {
        "source": "mdnbcd",
        "id": "api.WebGLRenderingContext.getTexParameter",
        "matched": "via-webfeatures"
      },
      {
        "source": "mdnbcd",
        "id": "api.WebGLRenderingContext.getUniform",
        "matched": "via-webfeatures"
      },
      {
        "source": "mdnbcd",
        "id": "api.WebGLRenderingContext.getUniformLocation",
        "matched": "via-webfeatures"
      },
      {
        "source": "mdnbcd",
        "id": "api.WebGLRenderingContext.getVertexAttrib",
        "matched": "via-webfeatures"
      },
      {
        "source": "mdnbcd",
        "id": "api.WebGLRenderingContext.getVertexAttribOffset",
        "matched": "via-webfeatures"
      },
      {
        "source": "mdnbcd",
        "id": "api.WebGLRenderingContext.hint",
        "matched": "via-webfeatures"
      },
      {
        "source": "mdnbcd",
        "id": "api.WebGLRenderingContext.isBuffer",
        "matched": "via-webfeatures"
      },
      {
        "source": "mdnbcd",
        "id": "api.WebGLRenderingContext.isContextLost",
        "matched": "via-webfeatures"
      },
      {
        "source": "mdnbcd",
        "id": "api.WebGLRenderingContext.isEnabled",
        "matched": "via-webfeatures"
      },
      {
        "source": "mdnbcd",
        "id": "api.WebGLRenderingContext.isFramebuffer",
        "matched": "via-webfeatures"
      },
      {
        "source": "mdnbcd",
        "id": "api.WebGLRenderingContext.isProgram",
        "matched": "via-webfeatures"
      },
      {
        "source": "mdnbcd",
        "id": "api.WebGLRenderingContext.isRenderbuffer",
        "matched": "via-webfeatures"
      },
      {
        "source": "mdnbcd",
        "id": "api.WebGLRenderingContext.isShader",
        "matched": "via-webfeatures"
      },
      {
        "source": "mdnbcd",
        "id": "api.WebGLRenderingContext.isTexture",
        "matched": "via-webfeatures"
      },
      {
        "source": "mdnbcd",
        "id": "api.WebGLRenderingContext.lineWidth",
        "matched": "via-webfeatures"
      },
      {
        "source": "mdnbcd",
        "id": "api.WebGLRenderingContext.linkProgram",
        "matched": "via-webfeatures"
      },
      {
        "source": "mdnbcd",
        "id": "api.WebGLRenderingContext.pixelStorei",
        "matched": "via-webfeatures"
      },
      {
        "source": "mdnbcd",
        "id": "api.WebGLRenderingContext.polygonOffset",
        "matched": "via-webfeatures"
      },
      {
        "source": "mdnbcd",
        "id": "api.WebGLRenderingContext.readPixels",
        "matched": "via-webfeatures"
      },
      {
        "source": "mdnbcd",
        "id": "api.WebGLRenderingContext.renderbufferStorage",
        "matched": "via-webfeatures"
      },
      {
        "source": "mdnbcd",
        "id": "api.WebGLRenderingContext.sampleCoverage",
        "matched": "via-webfeatures"
      },
      {
        "source": "mdnbcd",
        "id": "api.WebGLRenderingContext.scissor",
        "matched": "via-webfeatures"
      },
      {
        "source": "mdnbcd",
        "id": "api.WebGLRenderingContext.shaderSource",
        "matched": "via-webfeatures"
      },
      {
        "source": "mdnbcd",
        "id": "api.WebGLRenderingContext.stencilFunc",
        "matched": "via-webfeatures"
      },
      {
        "source": "mdnbcd",
        "id": "api.WebGLRenderingContext.stencilFuncSeparate",
        "matched": "via-webfeatures"
      },
      {
        "source": "mdnbcd",
        "id": "api.WebGLRenderingContext.stencilMask",
        "matched": "via-webfeatures"
      },
      {
        "source": "mdnbcd",
        "id": "api.WebGLRenderingContext.stencilMaskSeparate",
        "matched": "via-webfeatures"
      },
      {
        "source": "mdnbcd",
        "id": "api.WebGLRenderingContext.stencilOp",
        "matched": "via-webfeatures"
      },
      {
        "source": "mdnbcd",
        "id": "api.WebGLRenderingContext.stencilOpSeparate",
        "matched": "via-webfeatures"
      },
      {
        "source": "mdnbcd",
        "id": "api.WebGLRenderingContext.texImage2D",
        "matched": "via-webfeatures"
      },
      {
        "source": "mdnbcd",
        "id": "api.WebGLRenderingContext.texParameterf",
        "matched": "via-webfeatures"
      },
      {
        "source": "mdnbcd",
        "id": "api.WebGLRenderingContext.texParameteri",
        "matched": "via-webfeatures"
      },
      {
        "source": "mdnbcd",
        "id": "api.WebGLRenderingContext.texSubImage2D",
        "matched": "via-webfeatures"
      },
      {
        "source": "mdnbcd",
        "id": "api.WebGLRenderingContext.uniform1f",
        "matched": "via-webfeatures"
      },
      {
        "source": "mdnbcd",
        "id": "api.WebGLRenderingContext.uniform1fv",
        "matched": "via-webfeatures"
      },
      {
        "source": "mdnbcd",
        "id": "api.WebGLRenderingContext.uniform1i",
        "matched": "via-webfeatures"
      },
      {
        "source": "mdnbcd",
        "id": "api.WebGLRenderingContext.uniform1iv",
        "matched": "via-webfeatures"
      },
      {
        "source": "mdnbcd",
        "id": "api.WebGLRenderingContext.uniform2f",
        "matched": "via-webfeatures"
      },
      {
        "source": "mdnbcd",
        "id": "api.WebGLRenderingContext.uniform2fv",
        "matched": "via-webfeatures"
      },
      {
        "source": "mdnbcd",
        "id": "api.WebGLRenderingContext.uniform2i",
        "matched": "via-webfeatures"
      },
      {
        "source": "mdnbcd",
        "id": "api.WebGLRenderingContext.uniform2iv",
        "matched": "via-webfeatures"
      },
      {
        "source": "mdnbcd",
        "id": "api.WebGLRenderingContext.uniform3f",
        "matched": "via-webfeatures"
      },
      {
        "source": "mdnbcd",
        "id": "api.WebGLRenderingContext.uniform3fv",
        "matched": "via-webfeatures"
      },
      {
        "source": "mdnbcd",
        "id": "api.WebGLRenderingContext.uniform3i",
        "matched": "via-webfeatures"
      },
      {
        "source": "mdnbcd",
        "id": "api.WebGLRenderingContext.uniform3iv",
        "matched": "via-webfeatures"
      },
      {
        "source": "mdnbcd",
        "id": "api.WebGLRenderingContext.uniform4f",
        "matched": "via-webfeatures"
      },
      {
        "source": "mdnbcd",
        "id": "api.WebGLRenderingContext.uniform4fv",
        "matched": "via-webfeatures"
      },
      {
        "source": "mdnbcd",
        "id": "api.WebGLRenderingContext.uniform4i",
        "matched": "via-webfeatures"
      },
      {
        "source": "mdnbcd",
        "id": "api.WebGLRenderingContext.uniform4iv",
        "matched": "via-webfeatures"
      },
      {
        "source": "mdnbcd",
        "id": "api.WebGLRenderingContext.uniformMatrix2fv",
        "matched": "via-webfeatures"
      },
      {
        "source": "mdnbcd",
        "id": "api.WebGLRenderingContext.uniformMatrix3fv",
        "matched": "via-webfeatures"
      },
      {
        "source": "mdnbcd",
        "id": "api.WebGLRenderingContext.uniformMatrix4fv",
        "matched": "via-webfeatures"
      },
      {
        "source": "mdnbcd",
        "id": "api.WebGLRenderingContext.useProgram",
        "matched": "via-webfeatures"
      },
      {
        "source": "mdnbcd",
        "id": "api.WebGLRenderingContext.validateProgram",
        "matched": "via-webfeatures"
      },
      {
        "source": "mdnbcd",
        "id": "api.WebGLRenderingContext.vertexAttrib1f",
        "matched": "via-webfeatures"
      },
      {
        "source": "mdnbcd",
        "id": "api.WebGLRenderingContext.vertexAttrib1fv",
        "matched": "via-webfeatures"
      },
      {
        "source": "mdnbcd",
        "id": "api.WebGLRenderingContext.vertexAttrib2f",
        "matched": "via-webfeatures"
      },
      {
        "source": "mdnbcd",
        "id": "api.WebGLRenderingContext.vertexAttrib2fv",
        "matched": "via-webfeatures"
      },
      {
        "source": "mdnbcd",
        "id": "api.WebGLRenderingContext.vertexAttrib3f",
        "matched": "via-webfeatures"
      },
      {
        "source": "mdnbcd",
        "id": "api.WebGLRenderingContext.vertexAttrib3fv",
        "matched": "via-webfeatures"
      },
      {
        "source": "mdnbcd",
        "id": "api.WebGLRenderingContext.vertexAttrib4f",
        "matched": "via-webfeatures"
      },
      {
        "source": "mdnbcd",
        "id": "api.WebGLRenderingContext.vertexAttrib4fv",
        "matched": "via-webfeatures"
      },
      {
        "source": "mdnbcd",
        "id": "api.WebGLRenderingContext.vertexAttribPointer",
        "matched": "via-webfeatures"
      },
      {
        "source": "mdnbcd",
        "id": "api.WebGLRenderingContext.viewport",
        "matched": "via-webfeatures"
      },
      {
        "source": "mdnbcd",
        "id": "api.WebGLRenderingContext.worker_support",
        "matched": "via-webfeatures"
      },
      {
        "source": "mdnbcd",
        "id": "api.WebGLShader",
        "matched": "via-webfeatures"
      },
      {
        "source": "mdnbcd",
        "id": "api.WebGLShader.worker_support",
        "matched": "via-webfeatures"
      },
      {
        "source": "mdnbcd",
        "id": "api.WebGLShaderPrecisionFormat",
        "matched": "via-webfeatures"
      },
      {
        "source": "mdnbcd",
        "id": "api.WebGLShaderPrecisionFormat.precision",
        "matched": "via-webfeatures"
      },
      {
        "source": "mdnbcd",
        "id": "api.WebGLShaderPrecisionFormat.rangeMax",
        "matched": "via-webfeatures"
      },
      {
        "source": "mdnbcd",
        "id": "api.WebGLShaderPrecisionFormat.rangeMin",
        "matched": "via-webfeatures"
      },
      {
        "source": "mdnbcd",
        "id": "api.WebGLShaderPrecisionFormat.worker_support",
        "matched": "via-webfeatures"
      },
      {
        "source": "mdnbcd",
        "id": "api.WebGLTexture",
        "matched": "via-webfeatures"
      },
      {
        "source": "mdnbcd",
        "id": "api.WebGLTexture.worker_support",
        "matched": "via-webfeatures"
      },
      {
        "source": "mdnbcd",
        "id": "api.WebGLUniformLocation",
        "matched": "via-webfeatures"
      },
      {
        "source": "mdnbcd",
        "id": "api.WebGLUniformLocation.worker_support",
        "matched": "via-webfeatures"
      }
    ]
  },
  "caniuseUrl": "https://caniuse.com/?search=webgl"
}