{
  "id": "wf-eyedropper",
  "source": "webfeatures",
  "name": "Eyedropper",
  "description": "The EyeDropper API opens an eyedropper tool, a color picker that allows users to select a color from their screen.",
  "category": "Other",
  "mdn": "https://developer.mozilla.org/docs/Web/API/EyeDropper/open",
  "links": [],
  "support": {
    "chrome": {
      "current": "y",
      "firstFull": "96"
    },
    "edge": {
      "current": "y",
      "firstFull": "96"
    },
    "firefox": {
      "current": "n"
    },
    "safari": {
      "current": "n"
    },
    "opera": {
      "current": "y",
      "firstFull": "96"
    },
    "ie": {
      "current": "y",
      "firstFull": "96"
    },
    "ios_saf": {
      "current": "n"
    },
    "and_chr": {
      "current": "y",
      "firstFull": "96"
    },
    "samsung": {
      "current": "y",
      "firstFull": "96"
    },
    "and_ff": {
      "current": "n"
    }
  },
  "usage": {
    "global": {
      "full": 76.09,
      "partial": 0,
      "total": 76.09
    },
    "byBrowser": {
      "desktop": {
        "chrome": 26.93,
        "edge": 4.25,
        "opera": 0.79
      },
      "mobile": {
        "and_chr": 44.12
      }
    },
    "type": "estimated"
  },
  "baseline": false,
  "sourceData": {
    "primary": {
      "source": "webfeatures",
      "id": "eyedropper"
    },
    "supplementary": [
      {
        "source": "mdnbcd",
        "id": "api.EyeDropper",
        "matched": "via-webfeatures"
      },
      {
        "source": "mdnbcd",
        "id": "api.EyeDropper.EyeDropper",
        "matched": "via-webfeatures"
      },
      {
        "source": "mdnbcd",
        "id": "api.EyeDropper.open",
        "matched": "via-webfeatures"
      },
      {
        "source": "mdnbcd",
        "id": "api.EyeDropper.secure_context_required",
        "matched": "via-webfeatures"
      }
    ]
  }
}