{
  "id": "wf-font-synthesis-weight",
  "source": "webfeatures",
  "name": "font-synthesis-weight",
  "description": "The font-synthesis-weight CSS property sets whether or not the browser should synthesize bold typefaces when they're missing from the font.",
  "category": "Other",
  "mdn": "https://developer.mozilla.org/docs/Web/CSS/Reference/Properties/font-synthesis-weight",
  "links": [],
  "support": {
    "chrome": {
      "current": "y",
      "firstFull": "97"
    },
    "firefox": {
      "current": "y",
      "firstFull": "111"
    },
    "safari": {
      "current": "y",
      "firstFull": "16.4"
    },
    "edge": {
      "current": "y",
      "firstFull": "97"
    },
    "opera": {
      "current": "y",
      "firstFull": "97"
    },
    "ie": {
      "current": "y",
      "firstFull": "97"
    },
    "ios_saf": {
      "current": "y",
      "firstFull": "16.4"
    },
    "and_chr": {
      "current": "y",
      "firstFull": "97"
    },
    "samsung": {
      "current": "y",
      "firstFull": "97"
    },
    "and_ff": {
      "current": "y",
      "firstFull": "111"
    }
  },
  "usage": {
    "global": {
      "full": 90.73,
      "partial": 0,
      "total": 90.73
    },
    "byBrowser": {
      "desktop": {
        "chrome": 26.93,
        "firefox": 1.75,
        "safari": 1.23,
        "edge": 4.25,
        "opera": 0.79
      },
      "mobile": {
        "ios_saf": 11.35,
        "and_chr": 44.12,
        "and_ff": 0.31
      }
    },
    "type": "estimated"
  },
  "baseline": "high",
  "sourceData": {
    "primary": {
      "source": "webfeatures",
      "id": "font-synthesis-weight"
    },
    "supplementary": [
      {
        "source": "mdnbcd",
        "id": "css.properties.font-synthesis-weight",
        "matched": "via-webfeatures"
      },
      {
        "source": "mdnbcd",
        "id": "css.properties.font-synthesis-weight.auto",
        "matched": "via-webfeatures"
      },
      {
        "source": "mdnbcd",
        "id": "css.properties.font-synthesis-weight.none",
        "matched": "via-webfeatures"
      }
    ]
  },
  "caniuseUrl": "https://caniuse.com/?search=wf-font-synthesis-weight"
}