{
  "id": "wf-headings",
  "source": "webfeatures",
  "name": "<h1> through <h6>",
  "description": "The <h1> through <h6> HTML elements represent six levels of section headings, in order of decreasing importance.",
  "category": "Other",
  "spec": [
    "https://html.spec.whatwg.org/multipage/sections.html#the-h1,-h2,-h3,-h4,-h5,-and-h6-elements",
    "https://html.spec.whatwg.org/multipage/sections.html#htmlheadingelement"
  ],
  "mdn": "https://developer.mozilla.org/docs/Web/HTML/Reference/Elements/Heading_Elements",
  "links": [],
  "support": {
    "chrome": {
      "current": "y",
      "firstFull": "1",
      "versions": [
        {
          "version": "1",
          "status": "y"
        }
      ]
    },
    "firefox": {
      "current": "y",
      "firstFull": "1",
      "versions": [
        {
          "version": "1",
          "status": "y"
        }
      ]
    },
    "safari": {
      "current": "y",
      "firstFull": "3",
      "versions": [
        {
          "version": "3",
          "status": "y"
        }
      ]
    },
    "edge": {
      "current": "y",
      "firstFull": "12",
      "versions": [
        {
          "version": "12",
          "status": "y"
        }
      ]
    },
    "opera": {
      "current": "y",
      "firstFull": "1",
      "versions": [
        {
          "version": "1",
          "status": "y"
        }
      ]
    },
    "ie": {
      "current": "y",
      "firstFull": "12",
      "versions": [
        {
          "version": "12",
          "status": "y"
        }
      ]
    },
    "ios_saf": {
      "current": "y",
      "firstFull": "3",
      "versions": [
        {
          "version": "3",
          "status": "y"
        }
      ]
    },
    "and_chr": {
      "current": "y",
      "firstFull": "1",
      "versions": [
        {
          "version": "1",
          "status": "y"
        }
      ]
    },
    "samsung": {
      "current": "y",
      "firstFull": "1",
      "versions": [
        {
          "version": "1",
          "status": "y"
        }
      ]
    },
    "and_ff": {
      "current": "y",
      "firstFull": "1",
      "versions": [
        {
          "version": "1",
          "status": "y"
        }
      ]
    }
  },
  "usage": {
    "global": {
      "full": 94.44,
      "partial": 0,
      "total": 94.44
    },
    "byBrowser": {
      "desktop": {
        "chrome": 27.41,
        "firefox": 1.85,
        "safari": 1.42,
        "edge": 4.26,
        "opera": 0.91
      },
      "mobile": {
        "ios_saf": 12.23,
        "and_chr": 44.12,
        "samsung": 1.93,
        "and_ff": 0.31
      }
    },
    "type": "estimated"
  },
  "status": "other",
  "baseline": "high",
  "sourceData": {
    "primary": {
      "source": "webfeatures",
      "id": "headings"
    },
    "supplementary": [
      {
        "source": "mdnbcd",
        "id": "api.HTMLHeadingElement",
        "matched": "via-webfeatures"
      },
      {
        "source": "mdnbcd",
        "id": "html.elements.h1",
        "matched": "via-webfeatures"
      },
      {
        "source": "mdnbcd",
        "id": "html.elements.h2",
        "matched": "via-webfeatures"
      },
      {
        "source": "mdnbcd",
        "id": "html.elements.h3",
        "matched": "via-webfeatures"
      },
      {
        "source": "mdnbcd",
        "id": "html.elements.h4",
        "matched": "via-webfeatures"
      },
      {
        "source": "mdnbcd",
        "id": "html.elements.h5",
        "matched": "via-webfeatures"
      },
      {
        "source": "mdnbcd",
        "id": "html.elements.h6",
        "matched": "via-webfeatures"
      }
    ]
  }
}