{
  "id": "wf-highlightsfrompoint",
  "source": "webfeatures",
  "name": "Custom highlights from point",
  "description": "The CSS.highlights.highlightsFromPoint() method returns an array of Highlight objects at a specified point.",
  "category": "Other",
  "mdn": "https://developer.mozilla.org/docs/Web/API/HighlightRegistry/highlightsFromPoint",
  "links": [],
  "support": {
    "chr": {
      "current": "y",
      "firstFull": "140"
    },
    "edg": {
      "current": "y",
      "firstFull": "140"
    },
    "ffx": {
      "current": "n"
    },
    "saf": {
      "current": "n"
    },
    "opr": {
      "current": "y",
      "firstFull": "140"
    },
    "ie": {
      "current": "y",
      "firstFull": "140"
    },
    "ios_saf": {
      "current": "n"
    },
    "an_chr": {
      "current": "y",
      "firstFull": "140"
    },
    "smsg": {
      "current": "y",
      "firstFull": "140"
    },
    "an_ff": {
      "current": "n"
    }
  },
  "usage": {
    "global": {
      "full": 63.69,
      "partial": 0,
      "total": 63.69
    },
    "byBrowser": {
      "desktop": {
        "chr": 15.52,
        "edg": 4.05
      },
      "mobile": {
        "an_chr": 44.12
      }
    },
    "type": "estimated"
  },
  "baseline": false,
  "sourceData": {
    "primary": {
      "source": "webfeatures",
      "id": "highlightsfrompoint"
    },
    "supplementary": [
      {
        "source": "mdnbcd",
        "id": "api.HighlightRegistry.highlightsFromPoint",
        "matched": "via-webfeatures"
      }
    ]
  },
  "caniuseUrl": "https://caniuse.com/?search=wf-highlightsfrompoint"
}